{
  "todos":
  [
    {
      "userId": 1,
      "id": 1,
      "title": "delectus aut autem",
      "completed": false
    },
    {
      "userId": 1,
      "id": 2,
      "title": "quis ut nam facilis et officia qui",
      "completed": false
    },
    {
      "userId": 1,
      "id": 3,
      "title": "fugiat veniam minus",
      "completed": false
    },
    {
      "userId": 1,
      "id": 4,
      "title": "et porro tempora",
      "completed": true
    },
    {
      "userId": 1,
      "id": 5,
      "title": "laboriosam mollitia et enim quasi adipisci quia provident illum",
      "completed": false
    },
    {
      "userId": 1,
      "id": 6,
      "title": "qui ullam ratione quibusdam voluptatem quia omnis",
      "completed": false
    },
    {
      "userId": 1,
      "id": 7,
      "title": "illo expedita consequatur quia in",
      "completed": false
    },
    {
      "userId": 1,
      "id": 8,
      "title": "quo adipisci enim quam ut ab",
      "completed": true
    },
    {
      "userId": 1,
      "id": 9,
      "title": "molestiae perspiciatis ipsa",
      "completed": false
    },
    {
      "userId": 1,
      "id": 10,
      "title": "illo est ratione doloremque quia maiores aut",
      "completed": true
    }
  ],
 
  "companies": [
    {
      "id": 101,
      "logo":"https://www.cubainformacion.tv/storage/portadas/2016/01/66750-la-ciencia-en-servicio-del-comercio.jpg?t=1700083467",
      "name": "CIDCI Inc.",
      "address": {
        "street": "123 Tech Lane",
        "city": "Silicon Valley",
        "state": "CA"
      },
      "rating": 4.5
    },
    {
      "id": 102,
      "logo":"https://media.licdn.com/dms/image/C4E0BAQHTGgdoO46F-g/company-logo_200_200/0/1630589587674?e=1725494400&v=beta&t=P1mwK_m5WKav3RValIXZsUsivEfe9pNtBbsvfe0P6tQ",
      "name": "Data Solutions Inc.",
      "address": {
        "street": "456 Data Drive",
        "city": "New York",
        "state": "NY"
      },
      "rating": 4.7
    },
    {
      "id": 103,
      "logo":"https://media.licdn.com/dms/image/C4D0BAQF9zCV8xOu0QA/company-logo_200_200/0/1655761173779/labiome_tech_logo?e=1725494400&v=beta&t=Qi2PTma4qLZAwx8Kcqqbs-MY-9y_4uVPHhKh5pGqmNc",
      "name": "Innovative Products",
      "address": {
        "street": "789 Product Road",
        "city": "Austin",
        "state": "TX"
      },
      "rating": 4.6
    },
    {
      "id": 104,
      "logo":"https://media.licdn.com/dms/image/D560BAQFJANcNveon3g/company-logo_200_200/0/1709310943415/prabadin_corp_logo?e=1725494400&v=beta&t=jMGwl8wa4nuf0OfeLH5qJ9H24pkJIR61rezSxUz7Z5Y",
      "name": "Prabadin Corp.",
      "address": {
        "street": "321 Design Street",
        "city": "San Francisco",
        "state": "CA"
      },
      "rating": 4.8
    },
    {
      "id": 105,
      "logo":"https://media.licdn.com/dms/image/C4E0BAQFdOATxNNIpgg/company-logo_200_200/0/1630631160607/universidad_de_las_ciencias_informticas_logo?e=1725494400&v=beta&t=JAk3nuA3sErLXPemPZHgu9VcYU5PIzoWcac0BWANk80",
      "name": "Cloud Services Ltd.",
      "address": {
        "street": "654 Cloud Avenue",
        "city": "Seattle",
        "state": "WA"
      },
      "rating": 4.4
    }
  ],
  "jobs": [
    {
      "id": 1,
      "title": "Software Engineer",
      "description": "Develop and maintain software applications.",
      "techs": [
        "JavaScript",
        "React",
        "Node.js"
      ],
      "creationDate": "2024-05-01",
      "salaryRange": "$70K - $120K",
      "companyId": 101,
      "remote": "Remote"
    },
    {
      "id": 2,
      "title": "Backend Developer",
      "description": "Build and maintain server-side applications.",
      "techs": [
        "Java",
        "Spring",
        "Microservices"
      ],
      "creationDate": "2024-05-02",
      "salaryRange": "$75K - $125K",
      "companyId": 101,
      "remote": "Hybrid"
    },
    {
      "id": 3,
      "title": "Data Scientist",
      "description": "Analyze and interpret complex data sets.",
      "techs": [
        "Python",
        "Machine Learning",
        "Data Analysis"
      ],
      "creationDate": "2024-05-02",
      "salaryRange": "$80K - $130K",
      "companyId": 102,
      "remote": "On Site"
    },
    {
      "id": 4,
      "title": "Data Analyst",
      "description": "Prepare and analyze data for business insights.",
      "techs": [
        "SQL",
        "Excel",
        "Data Visualization"
      ],
      "creationDate": "2024-05-03",
      "salaryRange": "$65K - $110K",
      "companyId": 102,
      "remote": "Remote"
    },
    {
      "id": 5,
      "title": "Product Manager",
      "description": "Oversee product development and launch.",
      "techs": [
        "Product Management",
        "Agile",
        "Scrum"
      ],
      "creationDate": "2024-05-03",
      "salaryRange": "$90K - $140K",
      "companyId": 103,
      "remote": "Hybrid"
    },
    {
      "id": 6,
      "title": "Product Designer",
      "description": "Design and optimize product interfaces.",
      "techs": [
        "UI/UX",
        "Design",
        "Prototyping"
      ],
      "creationDate": "2024-05-04",
      "salaryRange": "$70K - $120K",
      "companyId": 103,
      "remote": "On Site"
    },
    {
      "id": 7,
      "title": "UX Designer",
      "description": "Design user interfaces and experiences.",
      "techs": [
        "UI/UX",
        "Design",
        "Prototyping"
      ],
      "creationDate": "2024-05-04",
      "salaryRange": "$60K - $100K",
      "companyId": 104,
      "remote": "Remote"
    },
    {
      "id": 8,
      "title": "Graphic Designer",
      "description": "Create visual concepts and designs.",
      "techs": [
        "Photoshop",
        "Illustrator",
        "Graphic Design"
      ],
      "creationDate": "2024-05-05",
      "salaryRange": "$55K - $95K",
      "companyId": 104,
      "remote": "Hybrid"
    },
    {
      "id": 9,
      "title": "DevOps Engineer",
      "description": "Manage and optimize infrastructure and deployments.",
      "techs": [
        "DevOps",
        "AWS",
        "Docker"
      ],
      "creationDate": "2024-05-05",
      "salaryRange": "$75K - $125K",
      "companyId": 105,
      "remote": "On Site"
    },
    {
      "id": 10,
      "title": "Cloud Architect",
      "description": "Design and implement cloud solutions.",
      "techs": [
        "Cloud Computing",
        "Azure",
        "Infrastructure"
      ],
      "creationDate": "2024-05-06",
      "salaryRange": "$85K - $135K",
      "companyId": 105,
      "remote": "Remote"
    }
  ]
  
}
